boilerplate/__init__.py
boilerplate/logger.py
boilerplate/mongodatabase.py
boilerplate/logging/__init__.py
boilerplate/logging/initializer.py
boilerplate/mongo/__init__.py
boilerplate/mongo/initializer.py
ivozzo_pyboilerplate-1.0.0.dist-info/LICENSE
ivozzo_pyboilerplate-1.0.0.dist-info/METADATA
ivozzo_pyboilerplate-1.0.0.dist-info/WHEEL
ivozzo_pyboilerplate-1.0.0.dist-info/top_level.txt
ivozzo_pyboilerplate-1.0.0.dist-info/RECORD
