Metadata-Version: 2.1
Name: ivozzo-pyboilerplate
Version: 1.0.0
Summary: Python boilerplate
Home-page:  https://github.com/ivozzo/ivozzo-pyBoilerplate
Author: ivozzo
License: UNKNOWN
Platform: UNKNOWN
Classifier: Programming Language :: Python :: 3
Classifier: License :: OSI Approved :: GNU General Public License v3 or later (GPLv3+)
Classifier: Operating System :: OS Independent
Requires-Python: >=3.9
